dsc40graph.py
dsc40graph-0.2.0.dist-info/LICENSE
dsc40graph-0.2.0.dist-info/METADATA
dsc40graph-0.2.0.dist-info/WHEEL
dsc40graph-0.2.0.dist-info/top_level.txt
dsc40graph-0.2.0.dist-info/RECORD
