Metadata-Version: 2.1
Name: dsc40graph
Version: 0.2.0
Summary: A simple graph library used in DSC 40B @ UCSD.
Home-page: https://github.com/eldridgejm/dsc40graph
Author: Justin Eldridge
Author-email: jeldridge@ucsd.edu
License: UNKNOWN
Platform: UNKNOWN
